ldsc-2.0.1.data/scripts/ldsc.py
ldsc-2.0.1.data/scripts/make_annot.py
ldsc-2.0.1.data/scripts/munge_sumstats.py
ldscore/__init__.py
ldscore/irwls.py
ldscore/jackknife.py
ldscore/ldscore.py
ldscore/parse.py
ldscore/regressions.py
ldscore/sumstats.py
ldsc-2.0.1.dist-info/LICENSE
ldsc-2.0.1.dist-info/METADATA
ldsc-2.0.1.dist-info/WHEEL
ldsc-2.0.1.dist-info/top_level.txt
ldsc-2.0.1.dist-info/RECORD
