Metadata-Version: 2.1
Name: ldsc
Version: 2.0.1
Summary: LD Score Regression (LDSC)
Home-page: http://github.com/bulik/ldsc
Author: Brendan Bulik-Sullivan and Hilary Finucane
Author-email: 
License: GPLv3
License-File: LICENSE
Requires-Dist: bitarray (>=2.6.0)
Requires-Dist: nose (>=1.3.7)
Requires-Dist: pybedtools (>=0.9.0)
Requires-Dist: scipy (>=1.9.2)
Requires-Dist: numpy (>=1.23.3)
Requires-Dist: pandas (>=1.5.0)
